{
    "Typing":
        {
            "male":"Audio/TypingMale",
            "female":"Audio/TypingFemale",
            "neutral":"Audio/Typewriter"
        },
    "BGM":
        {
            "lobby":"Audio/Court_Lobby",
            "test01":"Audio/Test_BGM01",
            "test02":"Audio/Test_BGM02"
        },
    "SFX":
        {
            "shock":"Audio/Test_Shock",
            "select":"Audio/Test_Select",
            "slam": "Audio/Test_Slam",
            "damage":"Audio/Test_Damage",
            "objection":"Audio/Test_Objection"
        }
}